odoo/addons/sale_order_line_description_name/LICENSE
odoo/addons/sale_order_line_description_name/README.rst
odoo/addons/sale_order_line_description_name/__init__.py
odoo/addons/sale_order_line_description_name/__manifest__.py
odoo/addons/sale_order_line_description_name/images/screen.png
odoo/addons/sale_order_line_description_name/models/__init__.py
odoo/addons/sale_order_line_description_name/models/sale_order_line.py
odoo/addons/sale_order_line_description_name/static/description/icon.png
odoo/addons/sale_order_line_description_name/static/description/index.html
odoo/addons/sale_order_line_description_name/tests/TEST_INSTRUCTIONS.rst
odoo_addon_sale_order_line_description_name-16.0.1.0.0.dist-info/METADATA
odoo_addon_sale_order_line_description_name-16.0.1.0.0.dist-info/WHEEL
odoo_addon_sale_order_line_description_name-16.0.1.0.0.dist-info/top_level.txt
odoo_addon_sale_order_line_description_name-16.0.1.0.0.dist-info/RECORD
